simplenote_jekyll/__init__.py
simplenote_jekyll/bin/__init__.py
simplenote_jekyll/bin/export.py
simplenote_jekyll-0.1.2.dist-info/DESCRIPTION.rst
simplenote_jekyll-0.1.2.dist-info/METADATA
simplenote_jekyll-0.1.2.dist-info/RECORD
simplenote_jekyll-0.1.2.dist-info/WHEEL
simplenote_jekyll-0.1.2.dist-info/entry_points.txt
simplenote_jekyll-0.1.2.dist-info/metadata.json
simplenote_jekyll-0.1.2.dist-info/top_level.txt
simplenote_jekyll-0.1.2.dist-info/zip-safe
