Metadata-Version: 2.0
Name: simplenote-jekyll
Version: 0.1.2
Summary: UNKNOWN
Home-page: https://github.com/thelonelyghost/simplenote_jekyll
Author: David Alexander
Author-email: opensource@thelonelyghost.com
License: MIT
Platform: UNKNOWN
Classifier: Development Status :: 1 - Planning
Classifier: Intended Audience :: End Users/Desktop
Classifier: License :: OSI Approved :: MIT License
Classifier: Programming Language :: Python :: 3
Classifier: Programming Language :: Python :: 3.6
Requires-Dist: simplenote
Provides-Extra: dev
Requires-Dist: pytest; extra == 'dev'
Requires-Dist: pytest-cov; extra == 'dev'
Requires-Dist: better-exceptions; extra == 'dev'
